activelog/__init__.py
activelog/activelog.py
activelog-1.0.1.dist-info/LICENSE
activelog-1.0.1.dist-info/METADATA
activelog-1.0.1.dist-info/WHEEL
activelog-1.0.1.dist-info/top_level.txt
activelog-1.0.1.dist-info/RECORD
