Metadata-Version: 2.1
Name: activelog
Version: 1.0.1
Summary: UNKNOWN
Home-page: https://github.com/AjxLab/ActiveLog
Author: Tatsuya Abe
Author-email: abe12@mccc.jp
License: MIT
Keywords: log logger logging
Platform: UNKNOWN
Classifier: License :: OSI Approved :: MIT License
Classifier: Programming Language :: Python :: 3.7
